zohal_sdk/__init__.py
zohal_sdk/client.py
zohal_sdk/constants.py
zohal_sdk/exceptions.py
zohal_sdk/models/__init__.py
zohal_sdk/models/account_to_iban.py
zohal_sdk/models/card_inquiry.py
zohal_sdk/models/card_to_account.py
zohal_sdk/models/card_to_iban.py
zohal_sdk/models/check_card_with_name.py
zohal_sdk/models/check_card_with_national_code.py
zohal_sdk/models/check_iban_with_name.py
zohal_sdk/models/iban.py
zohal_sdk/models/national_identity_inquery.py
zohal_sdk/models/persian_to_finglish.py
zohal_sdk/models/postal_code_inquiry.py
zohal_sdk/models/shahkar.py
zohal_sdk/services/__init__.py
zohal_sdk/services/inquiry.py
zohal_sdk/types/__init__.py
zohal_sdk/types/bank.py
zohal_sdk/types/base.py
zohal_sdk/types/finglish.py
zohal_sdk/types/matched.py
zohal_sdk/types/national_card.py
zohal_sdk/types/national_identity.py
zohal_sdk/types/postal.py
zohal_sdk/types/shahkar.py
zohal_sdk/utils/__init__.py
zohal_sdk/utils/url.py
zohal_sdk-0.1.1.dist-info/LICENSE
zohal_sdk-0.1.1.dist-info/METADATA
zohal_sdk-0.1.1.dist-info/WHEEL
zohal_sdk-0.1.1.dist-info/RECORD
