Metadata-Version: 2.1
Name: zohal-sdk
Version: 0.1.1
Summary: zohal-sdk is a Python SDK for interfacing with zohal.io.
Author: Alireza Rabie
Author-email: alireza@aazerra.dev
Requires-Python: >=3.8,<4.0
Classifier: Programming Language :: Python :: 3
Classifier: Programming Language :: Python :: 3.8
Classifier: Programming Language :: Python :: 3.9
Classifier: Programming Language :: Python :: 3.10
Classifier: Programming Language :: Python :: 3.11
Classifier: Programming Language :: Python :: 3.12
Classifier: Programming Language :: Python :: 3.13
Requires-Dist: dataclasses-json (>=0.6.7,<0.7.0)
Requires-Dist: requests (>=2.32.3,<3.0.0)
